vp4onnx/__init__.py
vp4onnx/__main__.py
vp4onnx/config.yml
vp4onnx/logconf.yml
vp4onnx/version.py
vp4onnx/app/__init__.py
vp4onnx/app/app.py
vp4onnx/app/client.py
vp4onnx/app/common.py
vp4onnx/app/redis.py
vp4onnx/app/server.py
vp4onnx/app/setting.py
vp4onnx/app/predicts/cls_EfficientNet_Lite4.py
vp4onnx/app/predicts/det_TinyYoloV3.py
vp4onnx/app/predicts/det_YoloV3.py
vp4onnx/app/predicts/det_YoloX.py
vp4onnx/app/predicts/det_YoloX_Lite.py
vp4onnx/scripts/vp4onnx.bat
vp4onnx/scripts/vp4onnx.sh
vp4onnx-0.1.2.data/scripts/vp4onnx.bat
vp4onnx-0.1.2.data/scripts/vp4onnx.sh
vp4onnx-0.1.2.dist-info/LICENSE
vp4onnx-0.1.2.dist-info/METADATA
vp4onnx-0.1.2.dist-info/WHEEL
vp4onnx-0.1.2.dist-info/top_level.txt
vp4onnx-0.1.2.dist-info/RECORD
