Metadata-Version: 2.1
Name: vp4onnx
Version: 0.1.2
Summary: vp4onnx: Perform inference using an image AI model in onnx format.
Home-page: https://github.com/hamacom2004jp/vp4onnx
Download-URL: https://github.com/hamacom2004jp/vp4onnx
Author: hamacom2004jp
Author-email: hamacom2004jp@gmail.com
Maintainer: hamacom2004jp
Maintainer-email: hamacom2004jp@gmail.com
License: MIT
Keywords: onnxruntime predict inference image ai model
Classifier: Development Status :: 4 - Beta
Classifier: Intended Audience :: Developers
Classifier: Intended Audience :: Information Technology
Classifier: Intended Audience :: System Administrators
Classifier: License :: OSI Approved :: MIT License
Classifier: Natural Language :: Japanese
Classifier: Programming Language :: Python
Classifier: Topic :: Utilities
License-File: LICENSE
Requires-Dist: motpy
Requires-Dist: onnxruntime
Requires-Dist: opencv-python
Requires-Dist: Pillow
Requires-Dist: pyyaml
Requires-Dist: redis
Requires-Dist: requests
Requires-Dist: tabulate
